footystats/__init__.py
footystats/database.py
footystats/debug.py
footystats/dev.py
footystats/leagues.py
footystats/match.py
footystats/nextmatches.py
footystats/sofascore.py
footystats/sources.py
footystats/team.py
footystats/testScrap.py
footystats/utils.py
footystats/webscrapping.py
footystats/whoscored.py
footystats-0.2.2.dist-info/licenses/LICENSE
venv/Lib/site-packages/__editable___footystats_0_2_0_finder.py
venv/Lib/site-packages/typing_extensions.py
venv/Lib/site-packages/_distutils_hack/__init__.py
venv/Lib/site-packages/_distutils_hack/override.py
venv/Lib/site-packages/bs4/__init__.py
venv/Lib/site-packages/bs4/_deprecation.py
venv/Lib/site-packages/bs4/_typing.py
venv/Lib/site-packages/bs4/_warnings.py
venv/Lib/site-packages/bs4/css.py
venv/Lib/site-packages/bs4/dammit.py
venv/Lib/site-packages/bs4/diagnose.py
venv/Lib/site-packages/bs4/element.py
venv/Lib/site-packages/bs4/exceptions.py
venv/Lib/site-packages/bs4/filter.py
venv/Lib/site-packages/bs4/formatter.py
venv/Lib/site-packages/bs4/py.typed
venv/Lib/site-packages/bs4/builder/__init__.py
venv/Lib/site-packages/bs4/builder/_html5lib.py
venv/Lib/site-packages/bs4/builder/_htmlparser.py
venv/Lib/site-packages/bs4/builder/_lxml.py
venv/Lib/site-packages/bs4/tests/__init__.py
venv/Lib/site-packages/bs4/tests/test_builder.py
venv/Lib/site-packages/bs4/tests/test_builder_registry.py
venv/Lib/site-packages/bs4/tests/test_css.py
venv/Lib/site-packages/bs4/tests/test_dammit.py
venv/Lib/site-packages/bs4/tests/test_element.py
venv/Lib/site-packages/bs4/tests/test_filter.py
venv/Lib/site-packages/bs4/tests/test_formatter.py
venv/Lib/site-packages/bs4/tests/test_fuzz.py
venv/Lib/site-packages/bs4/tests/test_html5lib.py
venv/Lib/site-packages/bs4/tests/test_htmlparser.py
venv/Lib/site-packages/bs4/tests/test_lxml.py
venv/Lib/site-packages/bs4/tests/test_navigablestring.py
venv/Lib/site-packages/bs4/tests/test_pageelement.py
venv/Lib/site-packages/bs4/tests/test_soup.py
venv/Lib/site-packages/bs4/tests/test_tag.py
footystats-0.2.2.dist-info/METADATA
footystats-0.2.2.dist-info/WHEEL
footystats-0.2.2.dist-info/top_level.txt
footystats-0.2.2.dist-info/RECORD
