Metadata-Version: 2.4
Name: footystats
Version: 0.2.2
Summary: grab soccer data and build databases
Author-email: MORENO <m_moreno@hotmail.fr>
License: MIT
Requires-Python: >=3.7
License-File: LICENSE
Dynamic: license-file
